ironbot/__init__.py
ironbot/__main__.py
ironbot/models.py
ironbot/parsers.py
ironbot/scrappers.py
ironbot-0.0.6.dist-info/LICENSE
ironbot-0.0.6.dist-info/METADATA
ironbot-0.0.6.dist-info/WHEEL
ironbot-0.0.6.dist-info/entry_points.txt
ironbot-0.0.6.dist-info/RECORD
