Metadata-Version: 2.1
Name: ironbot
Version: 0.0.6
Summary: CLI to get information about Ironman professional races
Home-page: https://github.com/cuducos/ironbot/
License: GPLv3
Keywords: triathlon,Ironamn,Professional triathletes,Professional triathlon races
Author: Eduardo Cuducos
Author-email: 4732915+cuducos@users.noreply.github.com
Requires-Python: >=3.9,<4.0
Classifier: Development Status :: 4 - Beta
Classifier: Intended Audience :: Developers
Classifier: Intended Audience :: Information Technology
Classifier: License :: Other/Proprietary License
Classifier: Programming Language :: Python :: 3
Classifier: Programming Language :: Python :: 3.9
Classifier: Programming Language :: Python :: 3.10
Classifier: Programming Language :: Python :: 3.11
Classifier: Programming Language :: Python :: 3.10
Classifier: Programming Language :: Python :: 3.11
Classifier: Programming Language :: Python :: 3.9
Classifier: Topic :: Utilities
Requires-Dist: alembic (>=1.11.1,<2.0.0)
Requires-Dist: beautifulsoup4 (>=4.12.2,<5.0.0)
Requires-Dist: camelot-py (>=0.11.0,<0.12.0)
Requires-Dist: ghostscript (>=0.7,<0.8)
Requires-Dist: opencv-python (>=4.7.0.72,<5.0.0.0)
Requires-Dist: sqlalchemy (>=2.0.15,<3.0.0)
Requires-Dist: typer (>=0.9.0,<0.10.0)
Project-URL: Repository, https://github.com/cuducos/ironbot/
